agentcube/__init__.py
agentcube/code_interpreter.py
agentcube/exceptions.py
agentcube/clients/__init__.py
agentcube/clients/control_plane.py
agentcube/clients/data_plane.py
agentcube/utils/__init__.py
agentcube/utils/http.py
agentcube/utils/log.py
agentcube/utils/utils.py
agentcube_sdk-0.0.10.dist-info/METADATA
agentcube_sdk-0.0.10.dist-info/WHEEL
agentcube_sdk-0.0.10.dist-info/top_level.txt
agentcube_sdk-0.0.10.dist-info/RECORD
