Metadata-Version: 2.4
Name: agentcube-sdk
Version: 0.0.10
Summary: Python SDK for AgentCube Code Interpreter
Requires-Dist: requests
Requires-Dist: PyJWT>=2.0.0
Requires-Dist: cryptography
